wizardlangid/__init__.py
wizardlangid/wizard_lang_id.py
wizardlangid/wizard_analyze_text/__init__.py
wizardlangid/wizard_analyze_text/wizard_lang_detect/__init__.py
wizardlangid/wizard_analyze_text/wizard_lang_detect/_utils.py
wizardlangid/wizard_analyze_text/wizard_lang_detect/detect_lang.py
wizardlangid/wizard_analyze_text/wizard_lang_detect/gating_scoring.py
wizardlangid/wizard_analyze_text/wizard_lang_detect/hints.py
wizardlangid/wizard_analyze_text/wizard_lang_detect/model_io.py
wizardlangid/wizard_analyze_text/wizard_lang_detect/lang_addons/__init__.py
wizardlangid/wizard_analyze_text/wizard_lang_detect/lang_addons/arabic_signature_letters.json
wizardlangid/wizard_analyze_text/wizard_lang_detect/lang_addons/diacritic_map.json
wizardlangid/wizard_analyze_text/wizard_lang_detect/lang_addons/letter_freq.json
wizardlangid/wizard_analyze_text/wizard_lang_detect/lang_addons/profiles.json
wizardlangid/wizard_analyze_text/wizard_lang_detect/lang_addons/profiles_trie_signature/__init__.py
wizardlangid/wizard_analyze_text/wizard_lang_detect/lang_addons/profiles_trie_signature/2/__init__.py
wizardlangid/wizard_analyze_text/wizard_lang_detect/lang_addons/profiles_trie_signature/2/fused.sig.trie.zst
wizardlangid/wizard_analyze_text/wizard_lang_detect/lang_addons/profiles_trie_signature/3/__init__.py
wizardlangid/wizard_analyze_text/wizard_lang_detect/lang_addons/profiles_trie_signature/3/fused.sig.trie.zst
wizardlangid/wizard_analyze_text/wizard_lang_detect/lang_addons/profiles_trie_signature/4/__init__.py
wizardlangid/wizard_analyze_text/wizard_lang_detect/lang_addons/profiles_trie_signature/4/fused.sig.trie.zst
wizardlangid/wizard_analyze_text/wizard_lang_detect/profiles_trie_kn/__init__.py
wizardlangid/wizard_analyze_text/wizard_lang_detect/profiles_trie_kn/meta.json.zst
wizardlangid/wizard_analyze_text/wizard_lang_detect/profiles_trie_kn/1/__init__.py
wizardlangid/wizard_analyze_text/wizard_lang_detect/profiles_trie_kn/1/fused.trie.zst
wizardlangid-1.0.0.dist-info/licenses/LICENSE
wizardlangid-1.0.0.dist-info/METADATA
wizardlangid-1.0.0.dist-info/WHEEL
wizardlangid-1.0.0.dist-info/top_level.txt
wizardlangid-1.0.0.dist-info/RECORD
