Metadata-Version: 2.4
Name: wizardlangid
Version: 1.0.0
Summary: Language identification via character n-gram profiles. Candidate gating guided by priors and linguistic cues, then probability estimation for each language. Supports 161 languages. Returns a top-1 ISO code or a probability-ordered list.
Author-email: Mattia Rubino <textwizard.dev@gmail.com>
License: WizardLangID — Copyright (C) 2024–2025 Mattia Rubino
Project-URL: Homepage, https://github.com/textwizard-dev/wizardlangid
Project-URL: Source, https://github.com/textwizard-dev/wizardlangid
Project-URL: Documentation, https://wizardlangid.readthedocs.io/en/latest/
Keywords: language-identification,language-detection,language-id,lid,langid,langdetect,character-ngrams,ngram,text-classification,nlp,multilingual,iso-639-1,iso-639-3,probabilistic,linguistic-cues
Classifier: Programming Language :: Python :: 3
Classifier: Programming Language :: Python :: 3.9
Classifier: Programming Language :: Python :: 3.10
Classifier: Programming Language :: Python :: 3.11
Classifier: Intended Audience :: Developers
Classifier: Topic :: Text Processing
Classifier: License :: OSI Approved :: GNU Affero General Public License v3 or later (AGPLv3+)
Requires-Python: >=3.9
License-File: LICENSE
Requires-Dist: marisa-trie>=1.3.0
Requires-Dist: zstandard>=0.22
Requires-Dist: regex>=2024.11.6
Dynamic: license-file
